src/dq_etl/__init__.py
src/dq_etl/config_parser.py
src/dq_etl/controller.py
src/dq_etl/destination_config.json
src/dq_etl/main.py
src/dq_etl/mysql_plugin/__init__.py
src/dq_etl/mysql_plugin/main.py
src/dq_etl/mysql_plugin/plugin.py
src/dq_etl/mysql_plugin/type_mapping.py
src/dq_etl/plugin_registry.py
src/dq_etl/postgres_plugin/__init__.py
src/dq_etl/postgres_plugin/main.py
src/dq_etl/postgres_plugin/plugin.py
src/dq_etl/postgres_plugin/type_mapping.py
src/dq_etl/setup.py
src/dq_etl/source_config.json
src/dq_etl/utility/__init__.py
src/dq_etl/utility/utils.py
dq_etl-0.1.3.dist-info/METADATA
dq_etl-0.1.3.dist-info/WHEEL
dq_etl-0.1.3.dist-info/entry_points.txt
dq_etl-0.1.3.dist-info/RECORD
